{
  "_lastRunAt": "2026-07-24T03:00:47.318Z",
  "SOL-USDT": {
    "signal": "WAITING_FOR_ZONE",
    "direction": "SELL",
    "price": 75.5,
    "bias1d": "BULLISH",
    "bias4h": "BEARISH",
    "bias1h": "BEARISH",
    "bias30m": "BEARISH",
    "bias15m": "BEARISH",
    "updatedAt": "2026-07-24T03:00:21.707Z"
  },
  "ETH-USDT": {
    "signal": "WAITING_FOR_ZONE",
    "direction": "SELL",
    "price": 1869.13,
    "bias1d": "BULLISH",
    "bias4h": "BULLISH",
    "bias1h": "BEARISH",
    "bias30m": "BEARISH",
    "bias15m": "BEARISH",
    "updatedAt": "2026-07-24T03:00:19.566Z"
  },
  "LINK-USDT": {
    "signal": "WAITING_FOR_ZONE",
    "direction": "SELL",
    "price": 8.4116,
    "bias1d": "NEUTRAL",
    "bias4h": "NEUTRAL",
    "bias1h": "BEARISH",
    "bias30m": "BEARISH",
    "bias15m": "BEARISH",
    "updatedAt": "2026-07-24T03:00:34.502Z"
  },
  "XRP-USDT": {
    "signal": "WAITING_FOR_ZONE",
    "direction": "SELL",
    "price": 1.10677,
    "bias1d": "BEARISH",
    "bias4h": "NEUTRAL",
    "bias1h": "NEUTRAL",
    "bias30m": "BEARISH",
    "bias15m": "BEARISH",
    "updatedAt": "2026-07-24T03:00:25.975Z"
  },
  "BTC-USDT": {
    "signal": "NO_AGREEMENT",
    "direction": null,
    "price": 65101.1,
    "bias1d": "NEUTRAL",
    "bias4h": "BULLISH",
    "bias1h": "NEUTRAL",
    "bias30m": "BEARISH",
    "bias15m": "BEARISH",
    "updatedAt": "2026-07-24T03:00:23.841Z"
  },
  "POL-USDT": {
    "signal": "WAITING_FOR_ZONE",
    "direction": "SELL",
    "price": 0.0768,
    "bias1d": "BEARISH",
    "bias4h": "BEARISH",
    "bias1h": "BEARISH",
    "bias30m": "BEARISH",
    "bias15m": "BEARISH",
    "updatedAt": "2026-07-24T03:00:45.187Z"
  },
  "DOGE-USDT": {
    "signal": "WAITING_FOR_ZONE",
    "direction": "SELL",
    "price": 0.06909,
    "bias1d": "BEARISH",
    "bias4h": "BEARISH",
    "bias1h": "BEARISH",
    "bias30m": "BEARISH",
    "bias15m": "BEARISH",
    "updatedAt": "2026-07-24T03:00:30.248Z"
  },
  "BNB-USDT": {
    "signal": "WAITING_FOR_ZONE",
    "direction": "SELL",
    "price": 566.801,
    "bias1d": "BEARISH",
    "bias4h": "BEARISH",
    "bias1h": "NEUTRAL",
    "bias30m": "BEARISH",
    "bias15m": "BEARISH",
    "updatedAt": "2026-07-24T03:00:36.651Z"
  },
  "LTC-USDT": {
    "signal": "WAITING_FOR_ZONE",
    "direction": "SELL",
    "price": 46.64,
    "bias1d": "BULLISH",
    "bias4h": "BULLISH",
    "bias1h": "BEARISH",
    "bias30m": "BEARISH",
    "bias15m": "BEARISH",
    "updatedAt": "2026-07-24T03:00:40.906Z"
  },
  "TRX-USDT": {
    "signal": "NO_AGREEMENT",
    "direction": null,
    "price": 0.3286,
    "bias1d": "BEARISH",
    "bias4h": "BULLISH",
    "bias1h": "NEUTRAL",
    "bias30m": "NEUTRAL",
    "bias15m": "BULLISH",
    "updatedAt": "2026-07-24T03:00:43.043Z"
  },
  "AVAX-USDT": {
    "signal": "WAITING_FOR_ZONE",
    "direction": "SELL",
    "price": 6.243,
    "bias1d": "BEARISH",
    "bias4h": "BEARISH",
    "bias1h": "BEARISH",
    "bias30m": "BEARISH",
    "bias15m": "BEARISH",
    "updatedAt": "2026-07-24T03:00:32.376Z"
  },
  "DOT-USDT": {
    "signal": "WAITING_FOR_ZONE",
    "direction": "SELL",
    "price": 0.8128,
    "bias1d": "BEARISH",
    "bias4h": "BEARISH",
    "bias1h": "BEARISH",
    "bias30m": "BEARISH",
    "bias15m": "BEARISH",
    "updatedAt": "2026-07-24T03:00:38.777Z"
  },
  "ADA-USDT": {
    "signal": "WAITING_FOR_ZONE",
    "direction": "SELL",
    "price": 0.1669,
    "bias1d": "NEUTRAL",
    "bias4h": "BEARISH",
    "bias1h": "BEARISH",
    "bias30m": "BEARISH",
    "bias15m": "BEARISH",
    "updatedAt": "2026-07-24T03:00:28.112Z"
  },
  "MNT-USDT": {
    "signal": "WAITING_FOR_ZONE",
    "direction": "SELL",
    "price": 0.4084,
    "bias1d": "BEARISH",
    "bias4h": "BEARISH",
    "bias1h": "BEARISH",
    "bias30m": "BEARISH",
    "bias15m": "NEUTRAL",
    "updatedAt": "2026-07-24T03:00:47.318Z"
  }
}