{
  "_lastRunAt": "2026-07-20T00:30:46.045Z",
  "SOL-USDT": {
    "signal": "WAITING_FOR_ZONE",
    "direction": "BUY",
    "price": 76.76,
    "bias1d": "BULLISH",
    "bias4h": "NEUTRAL",
    "bias1h": "BULLISH",
    "bias30m": "BULLISH",
    "bias15m": "BULLISH",
    "updatedAt": "2026-07-20T00:30:19.580Z"
  },
  "ETH-USDT": {
    "signal": "WAITING_FOR_ZONE",
    "direction": "BUY",
    "price": 1879.5,
    "bias1d": "BULLISH",
    "bias4h": "BULLISH",
    "bias1h": "BULLISH",
    "bias30m": "BULLISH",
    "bias15m": "BULLISH",
    "updatedAt": "2026-07-20T00:30:17.364Z"
  },
  "LINK-USDT": {
    "signal": "WAITING_FOR_ZONE",
    "direction": "BUY",
    "price": 8.4315,
    "bias1d": "BEARISH",
    "bias4h": "BULLISH",
    "bias1h": "BULLISH",
    "bias30m": "BULLISH",
    "bias15m": "BULLISH",
    "updatedAt": "2026-07-20T00:30:32.808Z"
  },
  "XRP-USDT": {
    "signal": "WAITING_FOR_ZONE",
    "direction": "BUY",
    "price": 1.09989,
    "bias1d": "BEARISH",
    "bias4h": "NEUTRAL",
    "bias1h": "BULLISH",
    "bias30m": "BULLISH",
    "bias15m": "BULLISH",
    "updatedAt": "2026-07-20T00:30:23.983Z"
  },
  "BTC-USDT": {
    "signal": "WAITING_FOR_ZONE",
    "direction": "BUY",
    "price": 64857.3,
    "bias1d": "NEUTRAL",
    "bias4h": "BULLISH",
    "bias1h": "BULLISH",
    "bias30m": "BULLISH",
    "bias15m": "BULLISH",
    "updatedAt": "2026-07-20T00:30:21.783Z"
  },
  "POL-USDT": {
    "signal": "WAITING_FOR_ZONE",
    "direction": "SELL",
    "price": 0.0811,
    "bias1d": "BEARISH",
    "bias4h": "NEUTRAL",
    "bias1h": "BEARISH",
    "bias30m": "BEARISH",
    "bias15m": "BULLISH",
    "updatedAt": "2026-07-20T00:30:43.842Z"
  },
  "DOGE-USDT": {
    "signal": "SCANNED",
    "price": 0.07282,
    "direction": "BUY",
    "voteTally": "3/5",
    "agreeing": [
      "1H",
      "30m",
      "15m"
    ],
    "bias1d": "BEARISH",
    "bias4h": "BEARISH",
    "bias1h": "BULLISH",
    "bias30m": "BULLISH",
    "bias15m": "BULLISH",
    "poc": 0.07228385,
    "vah": 0.07343555,
    "val": 0.07200465,
    "swingHigh": 0.0745,
    "swingLow": 0.07101,
    "atr1h": 0.0003846574156091838,
    "updatedAt": "2026-07-20T00:30:28.381Z"
  },
  "BNB-USDT": {
    "signal": "NO_AGREEMENT",
    "direction": null,
    "price": 571.403,
    "bias1d": "BEARISH",
    "bias4h": "BEARISH",
    "bias1h": "NEUTRAL",
    "bias30m": "BULLISH",
    "bias15m": "BULLISH",
    "updatedAt": "2026-07-20T00:30:35.009Z"
  },
  "LTC-USDT": {
    "signal": "WAITING_FOR_ZONE",
    "direction": "BUY",
    "price": 47.56,
    "bias1d": "BULLISH",
    "bias4h": "BULLISH",
    "bias1h": "BULLISH",
    "bias30m": "BULLISH",
    "bias15m": "BULLISH",
    "updatedAt": "2026-07-20T00:30:39.413Z"
  },
  "TRX-USDT": {
    "signal": "SCANNED",
    "price": 0.3269,
    "direction": "SELL",
    "voteTally": "3/5",
    "agreeing": [
      "1D",
      "4H",
      "15m"
    ],
    "bias1d": "BEARISH",
    "bias4h": "BEARISH",
    "bias1h": "BULLISH",
    "bias30m": "NEUTRAL",
    "bias15m": "BEARISH",
    "poc": 0.323447,
    "vah": 0.325955,
    "val": 0.322655,
    "swingHigh": 0.3281,
    "swingLow": 0.3215,
    "atr1h": 0.0005701457371370625,
    "updatedAt": "2026-07-20T00:30:41.609Z"
  },
  "AVAX-USDT": {
    "signal": "NO_AGREEMENT",
    "direction": null,
    "price": 6.51,
    "bias1d": "BEARISH",
    "bias4h": "NEUTRAL",
    "bias1h": "NEUTRAL",
    "bias30m": "NEUTRAL",
    "bias15m": "NEUTRAL",
    "updatedAt": "2026-07-20T00:30:30.607Z"
  },
  "DOT-USDT": {
    "signal": "WAITING_FOR_ZONE",
    "direction": "SELL",
    "price": 0.8196,
    "bias1d": "BEARISH",
    "bias4h": "BEARISH",
    "bias1h": "BEARISH",
    "bias30m": "NEUTRAL",
    "bias15m": "NEUTRAL",
    "updatedAt": "2026-07-20T00:30:37.218Z"
  },
  "ADA-USDT": {
    "signal": "NO_AGREEMENT",
    "direction": null,
    "price": 0.1671,
    "bias1d": "NEUTRAL",
    "bias4h": "BEARISH",
    "bias1h": "BULLISH",
    "bias30m": "NEUTRAL",
    "bias15m": "BULLISH",
    "updatedAt": "2026-07-20T00:30:26.186Z"
  },
  "MNT-USDT": {
    "signal": "WAITING_FOR_ZONE",
    "direction": "SELL",
    "price": 0.427,
    "bias1d": "BEARISH",
    "bias4h": "BEARISH",
    "bias1h": "BEARISH",
    "bias30m": "BULLISH",
    "bias15m": "BULLISH",
    "updatedAt": "2026-07-20T00:30:46.044Z"
  }
}