{
  "_lastRunAt": "2026-07-21T21:30:48.781Z",
  "SOL-USDT": {
    "signal": "WAITING_FOR_ZONE",
    "direction": "BUY",
    "price": 77.99,
    "bias1d": "BULLISH",
    "bias4h": "NEUTRAL",
    "bias1h": "BULLISH",
    "bias30m": "BULLISH",
    "bias15m": "BEARISH",
    "updatedAt": "2026-07-21T21:30:22.034Z"
  },
  "ETH-USDT": {
    "signal": "WAITING_FOR_ZONE",
    "direction": "BUY",
    "price": 1923.89,
    "bias1d": "BULLISH",
    "bias4h": "BULLISH",
    "bias1h": "BULLISH",
    "bias30m": "BULLISH",
    "bias15m": "NEUTRAL",
    "updatedAt": "2026-07-21T21:30:19.861Z"
  },
  "LINK-USDT": {
    "signal": "WAITING_FOR_ZONE",
    "direction": "BUY",
    "price": 8.6286,
    "bias1d": "NEUTRAL",
    "bias4h": "BULLISH",
    "bias1h": "BULLISH",
    "bias30m": "BULLISH",
    "bias15m": "BEARISH",
    "updatedAt": "2026-07-21T21:30:35.342Z"
  },
  "XRP-USDT": {
    "signal": "WAITING_FOR_ZONE",
    "direction": "BUY",
    "price": 1.14774,
    "bias1d": "BEARISH",
    "bias4h": "BULLISH",
    "bias1h": "BULLISH",
    "bias30m": "BULLISH",
    "bias15m": "NEUTRAL",
    "updatedAt": "2026-07-21T21:30:26.412Z"
  },
  "BTC-USDT": {
    "signal": "WAITING_FOR_ZONE",
    "direction": "BUY",
    "price": 66309,
    "bias1d": "NEUTRAL",
    "bias4h": "BULLISH",
    "bias1h": "BULLISH",
    "bias30m": "BULLISH",
    "bias15m": "NEUTRAL",
    "updatedAt": "2026-07-21T21:30:24.213Z"
  },
  "POL-USDT": {
    "signal": "WAITING_FOR_ZONE",
    "direction": "SELL",
    "price": 0.0802,
    "bias1d": "BEARISH",
    "bias4h": "NEUTRAL",
    "bias1h": "BEARISH",
    "bias30m": "BEARISH",
    "bias15m": "BEARISH",
    "updatedAt": "2026-07-21T21:30:46.317Z"
  },
  "DOGE-USDT": {
    "signal": "NO_AGREEMENT",
    "direction": null,
    "price": 0.07345,
    "bias1d": "BEARISH",
    "bias4h": "NEUTRAL",
    "bias1h": "BULLISH",
    "bias30m": "BULLISH",
    "bias15m": "NEUTRAL",
    "updatedAt": "2026-07-21T21:30:30.791Z"
  },
  "BNB-USDT": {
    "signal": "WAITING_FOR_ZONE",
    "direction": "BUY",
    "price": 573.394,
    "bias1d": "BEARISH",
    "bias4h": "BULLISH",
    "bias1h": "BULLISH",
    "bias30m": "BULLISH",
    "bias15m": "NEUTRAL",
    "updatedAt": "2026-07-21T21:30:37.526Z"
  },
  "LTC-USDT": {
    "signal": "WAITING_FOR_ZONE",
    "direction": "BUY",
    "price": 46.98,
    "bias1d": "BULLISH",
    "bias4h": "BULLISH",
    "bias1h": "BULLISH",
    "bias30m": "NEUTRAL",
    "bias15m": "BEARISH",
    "updatedAt": "2026-07-21T21:30:41.956Z"
  },
  "TRX-USDT": {
    "signal": "WAITING_FOR_ZONE",
    "direction": "BUY",
    "price": 0.3297,
    "bias1d": "BEARISH",
    "bias4h": "BULLISH",
    "bias1h": "BULLISH",
    "bias30m": "BULLISH",
    "bias15m": "BULLISH",
    "updatedAt": "2026-07-21T21:30:44.144Z"
  },
  "AVAX-USDT": {
    "signal": "NO_AGREEMENT",
    "direction": null,
    "price": 6.561,
    "bias1d": "NEUTRAL",
    "bias4h": "BEARISH",
    "bias1h": "NEUTRAL",
    "bias30m": "BULLISH",
    "bias15m": "BEARISH",
    "updatedAt": "2026-07-21T21:30:33.065Z"
  },
  "DOT-USDT": {
    "signal": "NO_AGREEMENT",
    "direction": null,
    "price": 0.8533,
    "bias1d": "BEARISH",
    "bias4h": "BULLISH",
    "bias1h": "NEUTRAL",
    "bias30m": "NEUTRAL",
    "bias15m": "NEUTRAL",
    "updatedAt": "2026-07-21T21:30:39.788Z"
  },
  "ADA-USDT": {
    "signal": "WAITING_FOR_ZONE",
    "direction": "BUY",
    "price": 0.1737,
    "bias1d": "NEUTRAL",
    "bias4h": "BULLISH",
    "bias1h": "BULLISH",
    "bias30m": "BULLISH",
    "bias15m": "NEUTRAL",
    "updatedAt": "2026-07-21T21:30:28.618Z"
  },
  "MNT-USDT": {
    "signal": "WAITING_FOR_ZONE",
    "direction": "BUY",
    "price": 0.4295,
    "bias1d": "BEARISH",
    "bias4h": "BEARISH",
    "bias1h": "BULLISH",
    "bias30m": "BULLISH",
    "bias15m": "BULLISH",
    "updatedAt": "2026-07-21T21:30:48.781Z"
  }
}