{
  "_lastRunAt": "2026-07-21T00:45:40.335Z",
  "SOL-USDT": {
    "signal": "WAITING_FOR_ZONE",
    "direction": "BUY",
    "price": 78.24,
    "bias1d": "BULLISH",
    "bias4h": "NEUTRAL",
    "bias1h": "BULLISH",
    "bias30m": "BULLISH",
    "bias15m": "BULLISH",
    "updatedAt": "2026-07-21T00:45:14.422Z"
  },
  "ETH-USDT": {
    "signal": "WAITING_FOR_ZONE",
    "direction": "BUY",
    "price": 1915.5,
    "bias1d": "BULLISH",
    "bias4h": "BULLISH",
    "bias1h": "BULLISH",
    "bias30m": "BULLISH",
    "bias15m": "BULLISH",
    "updatedAt": "2026-07-21T00:45:12.270Z"
  },
  "LINK-USDT": {
    "signal": "WAITING_FOR_ZONE",
    "direction": "BUY",
    "price": 8.6337,
    "bias1d": "NEUTRAL",
    "bias4h": "BULLISH",
    "bias1h": "BULLISH",
    "bias30m": "BULLISH",
    "bias15m": "BULLISH",
    "updatedAt": "2026-07-21T00:45:27.388Z"
  },
  "XRP-USDT": {
    "signal": "WAITING_FOR_ZONE",
    "direction": "BUY",
    "price": 1.11716,
    "bias1d": "BEARISH",
    "bias4h": "BULLISH",
    "bias1h": "BULLISH",
    "bias30m": "BULLISH",
    "bias15m": "BULLISH",
    "updatedAt": "2026-07-21T00:45:18.789Z"
  },
  "BTC-USDT": {
    "signal": "WAITING_FOR_ZONE",
    "direction": "BUY",
    "price": 65510.7,
    "bias1d": "NEUTRAL",
    "bias4h": "BULLISH",
    "bias1h": "BULLISH",
    "bias30m": "BULLISH",
    "bias15m": "BULLISH",
    "updatedAt": "2026-07-21T00:45:16.583Z"
  },
  "POL-USDT": {
    "signal": "NO_AGREEMENT",
    "direction": null,
    "price": 0.0805,
    "bias1d": "BEARISH",
    "bias4h": "NEUTRAL",
    "bias1h": "BEARISH",
    "bias30m": "NEUTRAL",
    "bias15m": "BULLISH",
    "updatedAt": "2026-07-21T00:45:38.182Z"
  },
  "DOGE-USDT": {
    "signal": "NO_AGREEMENT",
    "direction": null,
    "price": 0.07236,
    "bias1d": "BEARISH",
    "bias4h": "NEUTRAL",
    "bias1h": "BULLISH",
    "bias30m": "BULLISH",
    "bias15m": "NEUTRAL",
    "updatedAt": "2026-07-21T00:45:23.095Z"
  },
  "BNB-USDT": {
    "signal": "WAITING_FOR_ZONE",
    "direction": "BUY",
    "price": 573.07,
    "bias1d": "BEARISH",
    "bias4h": "BEARISH",
    "bias1h": "BULLISH",
    "bias30m": "BULLISH",
    "bias15m": "BULLISH",
    "updatedAt": "2026-07-21T00:45:29.597Z"
  },
  "LTC-USDT": {
    "signal": "WAITING_FOR_ZONE",
    "direction": "BUY",
    "price": 47.43,
    "bias1d": "BULLISH",
    "bias4h": "BULLISH",
    "bias1h": "BULLISH",
    "bias30m": "BULLISH",
    "bias15m": "BULLISH",
    "updatedAt": "2026-07-21T00:45:33.882Z"
  },
  "TRX-USDT": {
    "signal": "NO_AGREEMENT",
    "direction": null,
    "price": 0.3266,
    "bias1d": "BEARISH",
    "bias4h": "BEARISH",
    "bias1h": "BULLISH",
    "bias30m": "NEUTRAL",
    "bias15m": "BULLISH",
    "updatedAt": "2026-07-21T00:45:36.033Z"
  },
  "AVAX-USDT": {
    "signal": "WAITING_FOR_ZONE",
    "direction": "BUY",
    "price": 6.614,
    "bias1d": "NEUTRAL",
    "bias4h": "BULLISH",
    "bias1h": "BULLISH",
    "bias30m": "BULLISH",
    "bias15m": "BULLISH",
    "updatedAt": "2026-07-21T00:45:25.242Z"
  },
  "DOT-USDT": {
    "signal": "NO_AGREEMENT",
    "direction": null,
    "price": 0.8301,
    "bias1d": "BEARISH",
    "bias4h": "BEARISH",
    "bias1h": "NEUTRAL",
    "bias30m": "BULLISH",
    "bias15m": "BULLISH",
    "updatedAt": "2026-07-21T00:45:31.739Z"
  },
  "ADA-USDT": {
    "signal": "WAITING_FOR_ZONE",
    "direction": "BUY",
    "price": 0.1716,
    "bias1d": "NEUTRAL",
    "bias4h": "NEUTRAL",
    "bias1h": "BULLISH",
    "bias30m": "BULLISH",
    "bias15m": "BULLISH",
    "updatedAt": "2026-07-21T00:45:20.940Z"
  },
  "MNT-USDT": {
    "signal": "WAITING_FOR_ZONE",
    "direction": "SELL",
    "price": 0.4253,
    "bias1d": "BEARISH",
    "bias4h": "BEARISH",
    "bias1h": "BEARISH",
    "bias30m": "BULLISH",
    "bias15m": "NEUTRAL",
    "updatedAt": "2026-07-21T00:45:40.334Z"
  }
}