{
  "_lastRunAt": "2026-07-24T05:15:39.784Z",
  "SOL-USDT": {
    "signal": "WAITING_FOR_ZONE",
    "direction": "SELL",
    "price": 75.78,
    "bias1d": "BULLISH",
    "bias4h": "BEARISH",
    "bias1h": "BEARISH",
    "bias30m": "BEARISH",
    "bias15m": "BEARISH",
    "updatedAt": "2026-07-24T05:15:14.117Z"
  },
  "ETH-USDT": {
    "signal": "WAITING_FOR_ZONE",
    "direction": "SELL",
    "price": 1880.02,
    "bias1d": "BULLISH",
    "bias4h": "BULLISH",
    "bias1h": "BEARISH",
    "bias30m": "BEARISH",
    "bias15m": "BEARISH",
    "updatedAt": "2026-07-24T05:15:11.973Z"
  },
  "LINK-USDT": {
    "signal": "NO_AGREEMENT",
    "direction": null,
    "price": 8.4504,
    "bias1d": "NEUTRAL",
    "bias4h": "BULLISH",
    "bias1h": "BEARISH",
    "bias30m": "BEARISH",
    "bias15m": "NEUTRAL",
    "updatedAt": "2026-07-24T05:15:26.955Z"
  },
  "XRP-USDT": {
    "signal": "WAITING_FOR_ZONE",
    "direction": "SELL",
    "price": 1.10852,
    "bias1d": "BEARISH",
    "bias4h": "NEUTRAL",
    "bias1h": "BEARISH",
    "bias30m": "BEARISH",
    "bias15m": "BEARISH",
    "updatedAt": "2026-07-24T05:15:18.396Z"
  },
  "BTC-USDT": {
    "signal": "NO_AGREEMENT",
    "direction": null,
    "price": 65351.8,
    "bias1d": "NEUTRAL",
    "bias4h": "BULLISH",
    "bias1h": "NEUTRAL",
    "bias30m": "NEUTRAL",
    "bias15m": "BULLISH",
    "updatedAt": "2026-07-24T05:15:16.255Z"
  },
  "POL-USDT": {
    "signal": "WAITING_FOR_ZONE",
    "direction": "SELL",
    "price": 0.0773,
    "bias1d": "BEARISH",
    "bias4h": "BEARISH",
    "bias1h": "BEARISH",
    "bias30m": "BEARISH",
    "bias15m": "BEARISH",
    "updatedAt": "2026-07-24T05:15:37.646Z"
  },
  "DOGE-USDT": {
    "signal": "WAITING_FOR_ZONE",
    "direction": "SELL",
    "price": 0.06906,
    "bias1d": "BEARISH",
    "bias4h": "BEARISH",
    "bias1h": "BEARISH",
    "bias30m": "BEARISH",
    "bias15m": "BEARISH",
    "updatedAt": "2026-07-24T05:15:22.673Z"
  },
  "BNB-USDT": {
    "signal": "WAITING_FOR_ZONE",
    "direction": "SELL",
    "price": 567.278,
    "bias1d": "BEARISH",
    "bias4h": "BEARISH",
    "bias1h": "NEUTRAL",
    "bias30m": "BEARISH",
    "bias15m": "NEUTRAL",
    "updatedAt": "2026-07-24T05:15:29.097Z"
  },
  "LTC-USDT": {
    "signal": "NO_AGREEMENT",
    "direction": null,
    "price": 46.72,
    "bias1d": "BULLISH",
    "bias4h": "BULLISH",
    "bias1h": "NEUTRAL",
    "bias30m": "BEARISH",
    "bias15m": "BEARISH",
    "updatedAt": "2026-07-24T05:15:33.375Z"
  },
  "TRX-USDT": {
    "signal": "WAITING_FOR_ZONE",
    "direction": "BUY",
    "price": 0.3296,
    "bias1d": "BEARISH",
    "bias4h": "BULLISH",
    "bias1h": "BULLISH",
    "bias30m": "BULLISH",
    "bias15m": "BULLISH",
    "updatedAt": "2026-07-24T05:15:35.506Z"
  },
  "AVAX-USDT": {
    "signal": "WAITING_FOR_ZONE",
    "direction": "SELL",
    "price": 6.276,
    "bias1d": "BEARISH",
    "bias4h": "BEARISH",
    "bias1h": "BEARISH",
    "bias30m": "BEARISH",
    "bias15m": "NEUTRAL",
    "updatedAt": "2026-07-24T05:15:24.820Z"
  },
  "DOT-USDT": {
    "signal": "WAITING_FOR_ZONE",
    "direction": "SELL",
    "price": 0.8148,
    "bias1d": "BEARISH",
    "bias4h": "BEARISH",
    "bias1h": "BEARISH",
    "bias30m": "BEARISH",
    "bias15m": "BEARISH",
    "updatedAt": "2026-07-24T05:15:31.228Z"
  },
  "ADA-USDT": {
    "signal": "WAITING_FOR_ZONE",
    "direction": "SELL",
    "price": 0.1674,
    "bias1d": "NEUTRAL",
    "bias4h": "BEARISH",
    "bias1h": "BEARISH",
    "bias30m": "BEARISH",
    "bias15m": "BEARISH",
    "updatedAt": "2026-07-24T05:15:20.529Z"
  },
  "MNT-USDT": {
    "signal": "WAITING_FOR_ZONE",
    "direction": "SELL",
    "price": 0.4096,
    "bias1d": "BEARISH",
    "bias4h": "BEARISH",
    "bias1h": "BEARISH",
    "bias30m": "BEARISH",
    "bias15m": "BEARISH",
    "updatedAt": "2026-07-24T05:15:39.784Z"
  }
}