{
  "_lastRunAt": "2026-07-21T03:15:39.148Z",
  "SOL-USDT": {
    "signal": "WAITING_FOR_ZONE",
    "direction": "BUY",
    "price": 78.32,
    "bias1d": "BULLISH",
    "bias4h": "NEUTRAL",
    "bias1h": "BULLISH",
    "bias30m": "BULLISH",
    "bias15m": "BULLISH",
    "updatedAt": "2026-07-21T03:15:13.400Z"
  },
  "ETH-USDT": {
    "signal": "WAITING_FOR_ZONE",
    "direction": "BUY",
    "price": 1925.11,
    "bias1d": "BULLISH",
    "bias4h": "BULLISH",
    "bias1h": "BULLISH",
    "bias30m": "BULLISH",
    "bias15m": "BULLISH",
    "updatedAt": "2026-07-21T03:15:11.265Z"
  },
  "LINK-USDT": {
    "signal": "WAITING_FOR_ZONE",
    "direction": "BUY",
    "price": 8.6335,
    "bias1d": "NEUTRAL",
    "bias4h": "BULLISH",
    "bias1h": "BULLISH",
    "bias30m": "BULLISH",
    "bias15m": "BULLISH",
    "updatedAt": "2026-07-21T03:15:26.217Z"
  },
  "XRP-USDT": {
    "signal": "WAITING_FOR_ZONE",
    "direction": "BUY",
    "price": 1.1219,
    "bias1d": "BEARISH",
    "bias4h": "BULLISH",
    "bias1h": "BULLISH",
    "bias30m": "BULLISH",
    "bias15m": "BULLISH",
    "updatedAt": "2026-07-21T03:15:17.671Z"
  },
  "BTC-USDT": {
    "signal": "WAITING_FOR_ZONE",
    "direction": "BUY",
    "price": 65511.1,
    "bias1d": "NEUTRAL",
    "bias4h": "BULLISH",
    "bias1h": "BULLISH",
    "bias30m": "BULLISH",
    "bias15m": "BULLISH",
    "updatedAt": "2026-07-21T03:15:15.538Z"
  },
  "POL-USDT": {
    "signal": "NO_AGREEMENT",
    "direction": null,
    "price": 0.0805,
    "bias1d": "BEARISH",
    "bias4h": "NEUTRAL",
    "bias1h": "BEARISH",
    "bias30m": "NEUTRAL",
    "bias15m": "BULLISH",
    "updatedAt": "2026-07-21T03:15:37.000Z"
  },
  "DOGE-USDT": {
    "signal": "SCANNED",
    "price": 0.0727,
    "direction": "BUY",
    "voteTally": "3/5",
    "agreeing": [
      "1H",
      "30m",
      "15m"
    ],
    "bias1d": "BEARISH",
    "bias4h": "NEUTRAL",
    "bias1h": "BULLISH",
    "bias30m": "BULLISH",
    "bias15m": "BULLISH",
    "poc": 0.0722772,
    "vah": 0.0735572,
    "val": 0.0719956,
    "swingHigh": 0.07357,
    "swingLow": 0.07101,
    "atr1h": 0.0005015342058893196,
    "updatedAt": "2026-07-21T03:15:21.933Z"
  },
  "BNB-USDT": {
    "signal": "WAITING_FOR_ZONE",
    "direction": "BUY",
    "price": 574.275,
    "bias1d": "BEARISH",
    "bias4h": "BULLISH",
    "bias1h": "BULLISH",
    "bias30m": "BULLISH",
    "bias15m": "BULLISH",
    "updatedAt": "2026-07-21T03:15:28.351Z"
  },
  "LTC-USDT": {
    "signal": "WAITING_FOR_ZONE",
    "direction": "BUY",
    "price": 47.45,
    "bias1d": "BULLISH",
    "bias4h": "BULLISH",
    "bias1h": "BULLISH",
    "bias30m": "BULLISH",
    "bias15m": "BULLISH",
    "updatedAt": "2026-07-21T03:15:32.704Z"
  },
  "TRX-USDT": {
    "signal": "NO_AGREEMENT",
    "direction": null,
    "price": 0.3263,
    "bias1d": "BEARISH",
    "bias4h": "BEARISH",
    "bias1h": "BULLISH",
    "bias30m": "NEUTRAL",
    "bias15m": "BULLISH",
    "updatedAt": "2026-07-21T03:15:34.834Z"
  },
  "AVAX-USDT": {
    "signal": "WAITING_FOR_ZONE",
    "direction": "BUY",
    "price": 6.655,
    "bias1d": "NEUTRAL",
    "bias4h": "BULLISH",
    "bias1h": "BULLISH",
    "bias30m": "BULLISH",
    "bias15m": "BULLISH",
    "updatedAt": "2026-07-21T03:15:24.078Z"
  },
  "DOT-USDT": {
    "signal": "NO_AGREEMENT",
    "direction": null,
    "price": 0.8351,
    "bias1d": "BEARISH",
    "bias4h": "BEARISH",
    "bias1h": "NEUTRAL",
    "bias30m": "BULLISH",
    "bias15m": "BULLISH",
    "updatedAt": "2026-07-21T03:15:30.570Z"
  },
  "ADA-USDT": {
    "signal": "WAITING_FOR_ZONE",
    "direction": "BUY",
    "price": 0.171,
    "bias1d": "NEUTRAL",
    "bias4h": "NEUTRAL",
    "bias1h": "BULLISH",
    "bias30m": "BULLISH",
    "bias15m": "BULLISH",
    "updatedAt": "2026-07-21T03:15:19.801Z"
  },
  "MNT-USDT": {
    "signal": "WAITING_FOR_ZONE",
    "direction": "SELL",
    "price": 0.4255,
    "bias1d": "BEARISH",
    "bias4h": "BEARISH",
    "bias1h": "BEARISH",
    "bias30m": "BULLISH",
    "bias15m": "BULLISH",
    "updatedAt": "2026-07-21T03:15:39.148Z"
  }
}