{
  "_lastRunAt": "2026-07-19T15:00:47.270Z",
  "SOL-USDT": {
    "signal": "WAITING_FOR_ZONE",
    "direction": "BUY",
    "price": 76.44,
    "bias1d": "BULLISH",
    "bias4h": "NEUTRAL",
    "bias1h": "NEUTRAL",
    "bias30m": "BULLISH",
    "bias15m": "BULLISH",
    "updatedAt": "2026-07-19T15:00:21.482Z"
  },
  "ETH-USDT": {
    "signal": "WAITING_FOR_ZONE",
    "direction": "BUY",
    "price": 1875.11,
    "bias1d": "BULLISH",
    "bias4h": "BULLISH",
    "bias1h": "NEUTRAL",
    "bias30m": "BULLISH",
    "bias15m": "BULLISH",
    "updatedAt": "2026-07-19T15:00:19.343Z"
  },
  "LINK-USDT": {
    "signal": "WAITING_FOR_ZONE",
    "direction": "BUY",
    "price": 8.374,
    "bias1d": "BEARISH",
    "bias4h": "BULLISH",
    "bias1h": "NEUTRAL",
    "bias30m": "BULLISH",
    "bias15m": "BULLISH",
    "updatedAt": "2026-07-19T15:00:34.282Z"
  },
  "XRP-USDT": {
    "signal": "NO_AGREEMENT",
    "direction": null,
    "price": 1.09869,
    "bias1d": "BEARISH",
    "bias4h": "NEUTRAL",
    "bias1h": "NEUTRAL",
    "bias30m": "BULLISH",
    "bias15m": "BULLISH",
    "updatedAt": "2026-07-19T15:00:25.746Z"
  },
  "BTC-USDT": {
    "signal": "NO_AGREEMENT",
    "direction": null,
    "price": 64594.5,
    "bias1d": "NEUTRAL",
    "bias4h": "BULLISH",
    "bias1h": "NEUTRAL",
    "bias30m": "BULLISH",
    "bias15m": "NEUTRAL",
    "updatedAt": "2026-07-19T15:00:23.611Z"
  },
  "POL-USDT": {
    "signal": "WAITING_FOR_ZONE",
    "direction": "SELL",
    "price": 0.0808,
    "bias1d": "BEARISH",
    "bias4h": "NEUTRAL",
    "bias1h": "BEARISH",
    "bias30m": "BEARISH",
    "bias15m": "BEARISH",
    "updatedAt": "2026-07-19T15:00:45.139Z"
  },
  "DOGE-USDT": {
    "signal": "NO_AGREEMENT",
    "direction": null,
    "price": 0.07262,
    "bias1d": "BEARISH",
    "bias4h": "BEARISH",
    "bias1h": "NEUTRAL",
    "bias30m": "BULLISH",
    "bias15m": "BULLISH",
    "updatedAt": "2026-07-19T15:00:30.012Z"
  },
  "BNB-USDT": {
    "signal": "WAITING_FOR_ZONE",
    "direction": "SELL",
    "price": 569.578,
    "bias1d": "BEARISH",
    "bias4h": "BEARISH",
    "bias1h": "BEARISH",
    "bias30m": "NEUTRAL",
    "bias15m": "NEUTRAL",
    "updatedAt": "2026-07-19T15:00:36.417Z"
  },
  "LTC-USDT": {
    "signal": "WAITING_FOR_ZONE",
    "direction": "BUY",
    "price": 47.3,
    "bias1d": "BULLISH",
    "bias4h": "BULLISH",
    "bias1h": "BULLISH",
    "bias30m": "BULLISH",
    "bias15m": "BULLISH",
    "updatedAt": "2026-07-19T15:00:40.876Z"
  },
  "TRX-USDT": {
    "signal": "NO_AGREEMENT",
    "direction": null,
    "price": 0.3272,
    "bias1d": "NEUTRAL",
    "bias4h": "BEARISH",
    "bias1h": "BULLISH",
    "bias30m": "BULLISH",
    "bias15m": "NEUTRAL",
    "updatedAt": "2026-07-19T15:00:43.008Z"
  },
  "AVAX-USDT": {
    "signal": "WAITING_FOR_ZONE",
    "direction": "SELL",
    "price": 6.472,
    "bias1d": "BEARISH",
    "bias4h": "BEARISH",
    "bias1h": "BEARISH",
    "bias30m": "BEARISH",
    "bias15m": "BEARISH",
    "updatedAt": "2026-07-19T15:00:32.150Z"
  },
  "DOT-USDT": {
    "signal": "WAITING_FOR_ZONE",
    "direction": "SELL",
    "price": 0.8255,
    "bias1d": "BEARISH",
    "bias4h": "BEARISH",
    "bias1h": "BEARISH",
    "bias30m": "BEARISH",
    "bias15m": "BEARISH",
    "updatedAt": "2026-07-19T15:00:38.747Z"
  },
  "ADA-USDT": {
    "signal": "WAITING_FOR_ZONE",
    "direction": "BUY",
    "price": 0.1667,
    "bias1d": "NEUTRAL",
    "bias4h": "BEARISH",
    "bias1h": "BULLISH",
    "bias30m": "BULLISH",
    "bias15m": "BULLISH",
    "updatedAt": "2026-07-19T15:00:27.882Z"
  },
  "MNT-USDT": {
    "signal": "WAITING_FOR_ZONE",
    "direction": "SELL",
    "price": 0.4225,
    "bias1d": "BEARISH",
    "bias4h": "BEARISH",
    "bias1h": "BEARISH",
    "bias30m": "BEARISH",
    "bias15m": "BULLISH",
    "updatedAt": "2026-07-19T15:00:47.270Z"
  }
}